bpmn_neo4j/exceptions/base.py
bpmn_neo4j/neo4j/neo4j_repositories.py
bpmn_neo4j/parsers/json_parser.py
bpmn_neo4j/parsers/parser_factory.py
bpmn_neo4j/transformers/edges.py
bpmn_neo4j/transformers/graph_transformer.py
bpmn_neo4j/transformers/nodes.py
bpmn_neo4j/transformers/pool_lanes.py
bpmn_neo4j/transformers/transform_input_elements.py
bpmn_neo4j/utils/__init__.py
bpmn_neo4j/utils/logger.py
bpmn_neo4j/validators/bpmn_semantic_validator.py
bpmn_neo4j/validators/schema_validator.py
bpmn_neo4j_lib_test-0.0.6a0.dist-info/METADATA
bpmn_neo4j_lib_test-0.0.6a0.dist-info/WHEEL
bpmn_neo4j_lib_test-0.0.6a0.dist-info/top_level.txt
bpmn_neo4j_lib_test-0.0.6a0.dist-info/RECORD
