Metadata-Version: 2.4
Name: bpmn-neo4j-lib-test
Version: 0.0.6a0
Summary: Library untuk mengubah BPMN JSON menjadi Cypher queries untuk Neo4j
Author-email: Izzat Aji Androfaza <business.aji2022@gmail.com>
License: MIT
Requires-Python: >=3.8
Requires-Dist: neo4j>=5.19.0
Requires-Dist: dirtyjson>=1.0.8
Requires-Dist: demjson3>=3.0.6
Requires-Dist: jsonschema>=4.0.0
Requires-Dist: requests>=2.31.0
Requires-Dist: networkx>=3.3
Provides-Extra: dev
Requires-Dist: pytest; extra == "dev"
Requires-Dist: black; extra == "dev"
Requires-Dist: flake8; extra == "dev"
